propogation_exporter/__init__.py
propogation_exporter/__main__.py
propogation_exporter/cli.py
propogation_exporter/dns_utils.py
propogation_exporter/journal.py
propogation_exporter/metrics.py
propogation_exporter/zone.py
propogation_exporter-0.1.0.dist-info/METADATA
propogation_exporter-0.1.0.dist-info/WHEEL
propogation_exporter-0.1.0.dist-info/entry_points.txt
propogation_exporter-0.1.0.dist-info/top_level.txt
propogation_exporter-0.1.0.dist-info/RECORD
