Metadata-Version: 2.1
Name: propogation-exporter
Version: 0.1.0
Summary: Systemd journal reader and exporter
Requires-Python: >=3.6
Requires-Dist: systemd-python>=234
Requires-Dist: dnspython==1.15.0
Requires-Dist: PyYAML<6.0,>=5.4.1
Requires-Dist: prometheus-client<1.0,>=0.1.0
Provides-Extra: dev
Requires-Dist: pytest; extra == "dev"
Requires-Dist: pytest-cov; extra == "dev"
Requires-Dist: pytest-timeout; extra == "dev"
Requires-Dist: flake8; extra == "dev"
Requires-Dist: mypy; extra == "dev"
Requires-Dist: types-PyYAML; extra == "dev"
